Workbook

Sheet VPI-Mạnh
A1: Project Name | B1: 36FULLZ
A2: Module Name | B2: View Product Information (VPI) | D2: Vẽ các bảng kỹ thuật viết testcase bên dưới
A3: Created By | B3: Nguyen Van Duy Manh
A4: Creation Date | B4: 45976
A5: Reviewed By | B5: Team Lead | D5: Black box technique application table in word file named NguyenVanDuyManh.docx
A6: Reviewed Date | B6: 45983
A8: Test Case ID | B8: Description | C8: Precondition | D8: Test Steps | E8: Test Data | F8: Expected Result | G8: Actual Result | H8: Status | I8: Comments(if any)
A9: TC-VPI-01 | B9: View product details such as introduction, price, size,... | C9: Website is running | D9: 1. Open the browser 2. Access the URL | E9: product.php?sanpham_id=25 | F9: Display product information | G9: Display product information | H9: Pass | I9: Equivalence (1)
A10: TC-VPI-02 | B10: View product details such as introduction, price, size,... | C10: Website is running | D10: 1. Open the browser 2. Access the URL | E10: product.php?sanpham_id=54 | F10: Display product information | G10: Display product information | H10: Pass | I10: Equivalence (2)
A11: TC-VPI-03 | B11: View product details such as introduction, price, size,... | C11: Website is running | D11: 1. Open the browser 2. Access the URL | E11: product.php?sanpham_id=34 | F11: Display product information | G11: Display product information | H11: Pass | I11: Equivalence (1)
A12: TC-VPI-04 | B12: View product details such as introduction, price, size,... | C12: Website is running | D12: 1. Open the browser 2. Access the URL | E12: product.php?sanpham_id=79 | F12: Display product information | G12: Display product information | H12: Pass | I12: Equivalence (4)
A13: TC-VPI-05 | B13: View product details such as introduction, price, size,... | C13: Website is running | D13: 1. Open the browser 2. Access the URL | E13: product.php?sanpham_id=47 | F13: Display product information | G13: Display product information | H13: Pass | I13: Equivalence (1)
A14: TC-VPI-06 | B14: View product details such as introduction, price, size,... | C14: Website is running | D14: 1. Open the browser 2. Access the URL | E14: product.php?sanpham_id=68 | F14: Display product information | G14: Display product information | H14: Pass | I14: Equivalence (3)
A15: TC-VPI-07 | B15: View product details such as introduction, price, size,... | C15: Website is running | D15: 1. Open the browser 2. Access the URL | E15: product.php?sanpham_id=71 | F15: Display product information | G15: Product name not found | H15: Fail | I15: Equivalence (8)
A16: TC-VPI-08 | B16: View product details such as introduction, price, size,... | C16: Website is running | D16: 1. Open the browser 2. Access the URL | E16: product.php?sanpham_id=29 | F16: Display product information | G16: Product name not found | H16: Fail | I16: Equivalence (1)
A17: TC-VPI-09 | B17: View product details such as introduction, price, size,... | C17: Website is running | D17: 1. Open the browser 2. Access the URL | E17: product.php?sanpham_id=36 | F17: Display product information | G17: Display product information | H17: Pass | I17: Equivalence (6)
A18: TC-VPI-10 | B18: View product details such as introduction, price, size,... | C18: Website is running | D18: 1. Open the browser 2. Access the URL | E18: product.php?sanpham_id=abc | F18: Product name not found | G18: Product name not found | H18: Pass | I18: Equivalence (10)
A19: TC-VPI-11 | B19: View product details such as introduction, price, size,... | C19: Website is running | D19: 1. Open the browser 2. Access the URL | E19: product.php?sanpham_id=52 | F19: Product name not found | G19: Product name not found | H19: Pass | I19: Equivalence (6)
... A34: TC-VPI-26 | B34: View product details such as introduction, price, size,... | C34: Website is running | D34: 1. Open the browser 2. Access the URL | E34: product.php?sanpham_id=%3BDROP%20TABLE%20sanpham%3B | F34: Product name not found | G34: Product name not found | H34: Pass | I34: Equivalence (12)
G35: Pass | H35: =COUNTIF(H9:H34,"Pass") -> 23
G36: Fail | H36: =COUNTIF(H9:H34,"Fail") -> 3
G37: Pending | H37: =COUNTIF(H9:H34,"Pending") -> 0
G38: Total | H38: =SUM(H35:H37) -> 26

Sheet SP-Mạnh
A1: Project Name | B1: 36FULLZ
A2: Module Name | B2: Search Product (SP) | D2: Vẽ các bảng kỹ thuật viết testcase bên dưới
A3: Created By | B3: Nguyen Van Duy Manh
A4: Creation Date | B4: 45976
A5: Reviewed By | B5: Team Lead | D5: Black box technique application table in word file named NguyenVanDuyManh.docx
A6: Reviewed Date | B6: 45983
A8: Test Case ID | B8: Description | C8: Precondition | D8: Test Steps | E8: Test Data | F8: Expected Result | G8: Actual Result | H8: Status | I8: Comments(if any)
A9: TC-SP-01 | B9: Search for products based on keywords "áo" | C9: Website is running | D9: 1. Open the browser 2. Enter the item you are looking for in the search bar | E9: search.php | F9: Display a list of items that contain the search keyword "áo" | G9: Display a list of items that contain the search keyword "áo" | H9: Pass | I9: Equivalence (1)
A10: TC-SP-02 | B10: Search for products based on keywords "quần" | C10: Website is running | D10: 1. Open the browser 2. Enter the item you are looking for in the search bar | E10: search.php | F10: Display a list of items that contain the search keyword "quần" | G10: Display a list of items that contain the search keyword "quần" | H10: Pass | I10: Equivalence (1)
A11: TC-SP-03 | B11: Search for products based on keywords "mũ" | C11: Website is running | D11: 1. Open the browser 2. Enter the item you are looking for in the search bar | E11: search.php | F11: Display a list of items that contain the search keyword "mũ" | G11: Display a list of items that contain the search keyword "mũ" | H11: Pass | I11: Equivalence (1)
A12: TC-SP-04 | B12: Search for products based on keywords "polo" | C12: Website is running | D12: 1. Open the browser 2. Enter the item you are looking for in the search bar | E12: search.php | F12: Display a list of items that contain the search keyword "polo" | G12: Display a list of items that contain the search keyword "polo" | H12: Pass | I12: Equivalence (1)
A13: TC-SP-05 | B13: Search for products based on keywords "kẻ" | C13: Website is running | D13: 1. Open the browser 2. Enter the item you are looking for in the search bar | E13: search.php | F13: Display a list of items that contain the search keyword "kẻ" | G13: Display a list of items that contain the search keyword "kẻ" | H13: Pass | I13: Equivalence (1)
A14: TC-SP-06 | B14: Search for products based on keywords "cổ" | C14: Website is running | D14: 1. Open the browser 2. Enter the item you are looking for in the search bar | E14: search.php | F14: Display a list of items that contain the search keyword "cổ" | G14: Display a list of items that contain the search keyword "cổ" | H14: Pass | I14: Equivalence (1)
A15: TC-SP-07 | B15: Search for products based on keywords "thể thao" | C15: Website is running | D15: 1. Open the browser 2. Enter the item you are looking for in the search bar | E15: search.php | F15: Display a list of items that contain the search keyword "thể thao" | G15: Display a list of items that contain the search keyword "thể thao" | H15: Pass | I15: Equivalence (1)
A16: TC-SP-08 | B16: Search for products based on keywords "tay" | C16: Website is running | D16: 1. Open the browser 2. Enter the item you are looking for in the search bar | E16: search.php | F16: Display a list of items that contain the search keyword "tay" | G16: Display a list of items that contain the search keyword "tay" | H16: Pass | I16: Equivalence (1)
A17: TC-SP-09 | B17: Search for products based on keywords "váy" | C17: Website is running | D17: 1. Open the browser 2. Enter the item you are looking for in the search bar | E17: search.php | F17: Display a list of items that contain the search keyword "váy" | G17: Display a list of items that contain the search keyword "váy" | H17: Pass | I17: Equivalence (1)
A18: TC-SP-10 | B18: Search for products based on keywords "bông" | C18: Website is running | D18: 1. Open the browser 2. Enter the item you are looking for in the search bar | E18: search.php | F18: Display a list of items that contain the search keyword "bông" | G18: Display a list of items that contain the search keyword "bông" | H18: Pass | I18: Equivalence (1)
A19: TC-SP-11 | B19: Search for products based on keywords "" | C19: Website is running | D19: 1. Open the browser 2. Enter the item you are looking for in the search bar | E19: search.php | F19: Send notification "Trống, vui lòng nhập mặt hàng cần tìm" | G19: Display empty list | H19: Fail | I19: Equivalence (2)
... A26: TC-SP-18 | B26: Search for products based on keywords "asdfghjkl" | C26: Website is running | D26: 1. Open the browser 2. Enter the item you are looking for in the search bar | E26: search.php | F26: Display empty list | G26: Display empty list | H26: Pass | I26: Equivalence (6)
G27: Pass | H27: =COUNTIF(H9:H26,"Pass") -> 13
G28: Fail | H28: =COUNTIF(H9:H26,"Fail") -> 5
G29: Pending | H29: =COUNTIF(H10:H26,"Pending") -> 0
G30: Total | H30: =SUM(H27:H29) -> 18

Sheet P-Mạnh
A1: Project Name | B1: 36FULLZ
A2: Module Name | B2: Purchase (P) | D2: Vẽ các bảng kỹ thuật viết testcase bên dưới
A3: Created By | B3: Nguyen Van Duy Manh
A4: Creation Date | B4: 45976
A5: Reviewed By | B5: Team Lead | D5: Black box technique application table in word file named NguyenVanDuyManh.docx
A6: Reviewed Date | B6: 45983
A8: Test Case ID | B8: Description | C8: Precondition | D8: Test Steps | E8: Test Data | F8: Expected Result | G8: Actual Result | H8: Status | I8: Comments(if any)
A9: TC-P-01 | B9: Order based on the following information: Order based on the following information: Buy "áo", quantity 3, size M | C9: - Website is running - Account registered on the system | D9: 1. Open the browser 2. Log in 3. Enter the item you are looking for in the search bar 4. Select the item you want to buy 5. Select the quantity and size of clothes you need 6. Click purchase | E9: cart.php | F9: Display the temporary table of the selected item | G9: Display the temporary table of the selected item | H9: Pass | I9: Equivalence (1) (3), Boundary Decision Table (R1)
A10: TC-P-02 | B10: Order based on the following information: Buy 'quần', quantity 2, size XXL | C10: - Website is running - Account registered on the system | D10: 1. Open the browser 2. Log in 3. Enter the item you are looking for in the search bar 4. Select the item you want to buy 5. Select the quantity and size of clothes you need 6. Click purchase | E10: cart.php | F10: Display the temporary table of the selected item | G10: Display the temporary table of the selected item | H10: Pass | I10: Equivalence (1) (6), Boundary Decision Table (R1)
A11: TC-P-03 | B11: Order based on the following information: Buy "mũ", quantity 1, size L | C11: - Website is running - Account registered on the system | D11: 1. Open the browser 2. Log in 3. Enter the item you are looking for in the search bar 4. Select the item you want to buy 5. Select the quantity and size of clothes you need 6. Click purchase | E11: cart.php | F11: Display the temporary table of the selected item | G11: Display the temporary table of the selected item | H11: Pass | I11: Equivalence (1) (4), Boundary Decision Table (R1)
A12: TC-P-04 | B12: Order based on the following information: Buy "mũ", quantity 1, size L and "váy", quantity 1, size S | C12: - Website is running - Account registered on the system | D12: 1. Open the browser 2. Log in 3. Enter the item you are looking for in the search bar 4. Select the item you want to buy 5. Select the quantity and size of clothes you need 6. Click purchase | E12: cart.php | F12: Display the temporary table of the selected item | G12: Display the temporary table of the selected item | H12: Pass | I12: Equivalence (1) (2) (4), Boundary Decision Table (R1)
A13: TC-P-05 | B13: Order based on the following information: Buy "áo", quantity 1, size XL; "quần", quantity 1, size XXL; "tay", quantity 1, size S | C13: - Website is running - Account registered on the system | D13: 1. Open the browser 2. Log in 3. Enter the item you are looking for in the search bar 4. Select the item you want to buy 5. Select the quantity and size of clothes you need 6. Click purchase | E13: cart.php | F13: Display the temporary table of the selected item | G13: Display the temporary table of the selected item | H13: Pass | I13: Equivalence (1) (2) (5) (6), Boundary Decision Table (R1)
A14: TC-P-06 | B14: Order based on the following information: Buy "áo",quantity 1, but size is not selected | C14: - Website is running - Account registered on the system | D14: 1. Open the browser 2. Log in 3. Enter the item you are looking for in the search bar 4. Select the item you want to buy 5. Select the quantity and size of clothes you need 6. Click purchase | E14: cart.php | F14: Display information "Vui lòng chọn size*" | G14: Display information "Vui lòng chọn size*" | H14: Pass | I14: Equivalence (1) (13), Boundary Decision Table (R3)
A15: TC-P-07 | B15: Order based on the following information: Buy "áo" but quantity is "abc", size XL | C15: - Website is running - Account registered on the system | D15: 1. Open the browser 2. Log in 3. Enter the item you are looking for in the search bar 4. Select the item you want to buy 5. Select the quantity and size of clothes you need 6. Click purchase | E15: cart.php | F15: Display information "Vui lòng nhập số" | G15: Display the temporary table of the selected item | H15: Fail | I15: Equivalence (9) (5), Boundary Decision Table (R2)
A16: TC-P-08 | B16: Order based on the following information: Buy "áo", but quantity is "@#$", size XL | C16: - Website is running - Account registered on the system | D16: 1. Open the browser 2. Log in 3. Enter the item you are looking for in the search bar 4. Select the item you want to buy 5. Select the quantity and size of clothes you need 6. Click purchase | E16: cart.php | F16: Display information "Vui lòng nhập số" | G16: Display the temporary table of the selected item | H16: Fail | I16: Equivalence (12) (5), Boundary Decision Table (R2)
A17: TC-P-09 | B17: Order based on the following information: Buy "áo", quantity is "999", size XL | C17: - Website is running - Account registered on the system | D17: 1. Open the browser 2. Log in 3. Enter the item you are looking for in the search bar 4. Select the item you want to buy 5. Select the quantity and size of clothes you need 6. Click purchase | E17: cart.php | F17: Display information "Số lượng đặt hàng phải nhỏ hơn số lượng tồn kho" | G17: Display information "Số lượng đặt hàng phải nhỏ hơn số lượng tồn kho" | H17: Pass | I17: Equivalence (8) (5), Boundary Decision Table (R2)
A18: TC-P-10 | B18: Order based on the following information: Buy "áo", quantity is "0", size XL | C18: - Website is running - Account registered on the system | D18: 1. Open the browser 2. Log in 3. Enter the item you are looking for in the search bar 4. Select the item you want to buy 5. Select the quantity and size of clothes you need 6. Click purchase | E18: cart.php | F18: Display information "Vui lòng nhập số lượng lớn hơn 0" | G18: Display the temporary table of the selected item | H18: Fail | I18: Equivalence (7) (5), Boundary Decision Table (R2)
A19: TC-P-11 | B19: Order based on the following information: Buy "áo", quantity is "-5", size XL | C19: - Website is running - Account registered on the system | D19: 1. Open the browser 2. Log in 3. Enter the item you are looking for in the search bar 4. Select the item you want to buy 5. Select the quantity and size of clothes you need 6. Click purchase | E19: cart.php | F19: Display information "Vui lòng nhập số lượng lớn hơn 0" | G19: Display the temporary table of the selected item | H19: Fail | I19: Equivalence (7) (5), Boundary Decision Table (R2)
... A22: TC-P-14 | B22: Order based on the following information: Buy "áo", quantity is "999", size is not selected | C22: - Website is running - Account registered on the system | D22: 1. Open the browser 2. Log in 3. Enter the item you are looking for in the search bar 4. Select the item you want to buy 5. Select the quantity and size of clothes you need 6. Click purchase | E22: cart.php | F22: Display information "Vui lòng chọn size*" | G22: Display information "Vui lòng chọn size*" | H22: Pass | I22: Equivalence (11) (5), Boundary Decision Table (R4)
G23: Pass | H23: =COUNTIF(H9:H22,"Pass") -> 8
G24: Fail | H24: =COUNTIF(H9:H22,"Fail") -> 6
G25: Pending | H25: =COUNTIF(H9:H22,"Pending") -> 0
G26: Total | H26: =SUM(H23:H25) -> 14

Sheet SPM-Mạnh
A1: Project Name | B1: 36FULLZ
A2: Module Name | B2: Select Payment Method (SPM) | D2: Vẽ các bảng kỹ thuật viết testcase bên dưới
A3: Created By | B3: Nguyen Van Duy Manh
A4: Creation Date | B4: 45976
A5: Reviewed By | B5: Team Lead
A6: Reviewed Date | B6: 45983
A8: Test Case ID | B8: Description | C8: Precondition | D8: Test Steps | E8: Test Data | F8: Expected Result | G8: Actual Result | H8: Status | I8: Comments(if any)
A9: TC-SPM-01 | B9: Select credit card payment method | C9: - Website is running - Account registered on the system | D9: 1. Open the browser 2. Log in 3. Enter the item you are looking for in the search bar 4. Select the item you want to buy 5. Select the quantity and size of clothes you need 6. Click purchase 7. Click to pay 8. Select payment method | E9: pay.php success.php | F9: Show successful payment notification and wait for delivery time | G9: Display QR code payment page | H9: Fail | I9: Error Guessing
A10: TC-SPM-02 | B10: Select payment method by Momo | C10: - Website is running - Account registered on the system | D10: 1. Open the browser 2. Log in 3. Enter the item you are looking for in the search bar 4. Select the item you want to buy 5. Select the quantity and size of clothes you need 6. Click purchase 7. Click to pay 8. Select payment method | E10: pay.php success.php | F10: Show successful payment notification and wait for delivery time | G10: Show successful payment notification and wait for delivery time | H10: Pass | I10: Error Guessing
A11: TC-SPM-03 | B11: Select payment method by ATM card | C11: - Website is running - Account registered on the system | D11: 1. Open the browser 2. Log in 3. Enter the item you are looking for in the search bar 4. Select the item you want to buy 5. Select the quantity and size of clothes you need 6. Click purchase 7. Click to pay 8. Select payment method | E11: pay.php success.php | F11: Show successful payment notification and wait for delivery time | G11: Display QR code payment page | H11: Fail | I11: Error Guessing
A12: TC-SPM-04 | B12: Choose cash on delivery payment method | C12: - Website is running - Account registered on the system | D12: 1. Open the browser 2. Log in 3. Enter the item you are looking for in the search bar 4. Select the item you want to buy 5. Select the quantity and size of clothes you need 6. Click purchase 7. Click to pay 8. Select payment method | E12: pay.php success.php | F12: Show successful payment notification and wait for delivery time | G12: Show successful payment notification and wait for delivery time | H12: Pass | I12: Error Guessing
G13: Pass | H13: =COUNTIF(H9:H12,"Pass") -> 2
G14: Fail | H14: =COUNTIF(H9:H12,"Fail") -> 2
G15: Pending | H15: =COUNTIF(H10:H12,"Pending") -> 0
G16: Total | H16: =SUM(H13:H15) -> 4

Sheet MC-Mạnh
A1: Project Name | B1: 36FULLZ
A2: Module Name | B2: Manage Comments (MC) | D2: Vẽ các bảng kỹ thuật viết testcase bên dưới
A3: Created By | B3: Nguyen Van Duy Manh
A4: Creation Date | B4: 45976
A5: Reviewed By | B5: Team Lead
A6: Reviewed Date | B6: 45983
A8: Test Case ID | B8: Description | C8: Precondition | D8: Test Steps | E8: Test Data | F8: Expected Result | G8: Actual Result | H8: Status | I8: Comments(if any)
A9: TC-MC-01 | B9: View list of customers who commented | C9: - Website is running - Must have administrator account | D9: 1. Open the browser 2. Log in admin 3. Select "Quản lí bình luận" function 4. Select "DS Khách Hàng Bình Luận" function on the toolbar | E9: binhluanAll.php | F9: Show a list of people who commented | G9: Show a list of people who commented | H9: Pass | I9: Error Guessing
A10: TC-MC-02 | B10: View list of checked comments | C10: - Website is running - Must have administrator account | D10: 1. Open the browser 2. Log in admin 3. Select "Quản lí bình luận" function 4. Select "Đã Kiểm Tra" function on the toolbar | E10: binhluanAll.php binhluandone.php | F10: Show a list of people who commented | G10: Show a list of people who commented | H10: Pass | I10: Error Guessing
A11: TC-MC-03 | B11: View list of unverified comments | C11: - Website is running - Must have administrator account | D11: 1. Open the browser 2. Log in admin 3. Select "Quản lí bình luận" function 4. Select "Chưa Kiểm Tra" function on the toolbar | E11: binhluanAll.php binhluanlist.php | F11: Show a list of people who commented | G11: Show a list of people who commented | H11: Pass | I11: Error Guessing
A12: TC-MC-04 | B12: Delete comment | C12: - Website is running - Must have administrator account | D12: 1. Open the browser 2. Log in admin 3. Select "Quản lí bình luận" function 4. Click the "recycle bin" icon to delete the comment | E12: binhluanAll.php | F12: Comment has been deleted | G12: 'Error because the user id comment to delete was not found | H12: Fail | I12: Error Guessing
G13: Pass | H13: =COUNTIF(H9:H12,"Pass") -> 3
G14: Fail | H14: =COUNTIF(H9:H12,"Fail") -> 1
G15: Pending | H15: =COUNTIF(H10:H12,"Pending") -> 0
G16: Total | H16: =SUM(H13:H15) -> 4

Sheet MPR-Mạnh
A1: Project Name | B1: 36FULLZ
A2: Module Name | B2: Manage Product Reviews (MPR) | D2: Vẽ các bảng kỹ thuật viết testcase bên dưới
A3: Created By | B3: Nguyen Van Duy Manh
A4: Creation Date | B4: 45976
A5: Reviewed By | B5: Team Lead
A6: Reviewed Date | B6: 45983
A8: Test Case ID | B8: Description | C8: Precondition | D8: Test Steps | E8: Test Data | F8: Expected Result | G8: Actual Result | H8: Status | I8: Comments(if any)
A9: TC-MPR-01 | B9: See list of all reviewed products | C9: - Website is running - Must have administrator account | D9: 1. Open the browser 2. Log in admin 3. Select "Đánh giá sản phẩm" function | E9: rating.php | F9: Display a list of rated products | G9: Display a list of rated products | H9: Pass | I9: Error Guessing
A10: TC-MPR-02 | B10: View customer reviews | C10: - Website is running - Must have administrator account | D10: 1. Open the browser 2. Log in admin 3. Select "Đánh giá sản phẩm" function 4. Click the "Xem" button on the toolbar | E10: rating.php register_rating.php | F10: Display product reviewer information | G10: Display product reviewer information | H10: Pass | I10: Error Guessing
A11: TC-MPR-03 | B11: Delete product review | C11: - Website is running - Must have administrator account | D11: 1. Open the browser 2. Log in admin 3. Select "Đánh giá sản phẩm" function 4. Click the "recycle bin" icon to delete the review | E11: rating.php | F11: Product review has been deleted | G11: Error because the user product id to delete was not found | H11: Fail | I11: Error Guessing
G12: Pass | H12: =COUNTIF(H9:H11,"Pass") -> 2
G13: Fail | H13: =COUNTIF(H9:H11,"Fail") -> 1
G14: Pending | H14: =COUNTIF(H10:H11,"Pending") -> 0
G15: Total | H15: =SUM(H12:H14) -> 3

Sheet VFP-Mạnh
A1: Project Name | B1: 36FULLZ
A2: Module Name | B2: View Favorite Products (VFP) | D2: Vẽ các bảng kỹ thuật viết testcase bên dưới
A3: Created By | B3: Nguyen Van Duy Manh
A4: Creation Date | B4: 45976
A5: Reviewed By | B5: Team Lead
A6: Reviewed Date | B6: 45983
A8: Test Case ID | B8: Description | C8: Precondition | D8: Test Steps | E8: Test Data | F8: Expected Result | G8: Actual Result | H8: Status | I8: Comments(if any)
A9: TC-VFP-01 | B9: View information about customers who have liked the product | C9: - Website is running - Must have administrator account | D9: 1. Open the browser 2. Log in admin 3. Select "Sản phẩm yêu thích" function 4. Click the "Xem" button on the toolbar | E9: wishlist.php register_wishlist.php | F9: Display information about customers who have liked the product | G9: Display information about customers who have liked the product | H9: Pass | I9: Error Guessing
A10: TC-VFP-02 | B10: Remove favorite products from list | C10: - Website is running - Must have administrator account | D10: 1. Open the browser 2. Log in admin 3. Select "Sản phẩm yêu thích" function 4. Click the "recycle bin" icon to delete the view favorite product | E10: wishlist.php | F10: Favorite product removed from favorites list | G10: Error because the ID of the favorite product to be deleted was not found | H10: Fail | I10: Error Guessing
A11: TC-VFP-03 | B11: View all favorite products | C11: - Website is running - Must have administrator account | D11: 1. Open the browser 2. Log in admin 3. Select "Sản phẩm yêu thích" function | E11: wishlist.php | F11: Display all favorite products of the website | G11: Display all favorite products of the website | H11: Pass | I11: Error Guessing
G12: Pass | H12: =COUNTIF(H9:H11,"Pass") -> 2
G13: Fail | H13: =COUNTIF(H9:H11,"Fail") -> 1
G14: Pending | H14: =COUNTIF(H10:H11,"Pending") -> 0
G15: Total | H15: =SUM(H12:H14) -> 3

Sheet MS-Mạnh
A1: Project Name | B1: 36FULLZ
A2: Module Name | B2: Manage Slide (MS) | D2: Vẽ các bảng kỹ thuật viết testcase bên dưới
A3: Created By | B3: Nguyen Van Duy Manh
A4: Creation Date | B4: 45976
A5: Reviewed By | B5: Team Lead
A6: Reviewed Date | B6: 45983
A8: Test Case ID | B8: Description | C8: Precondition | D8: Test Steps | E8: Test Data | F8: Expected Result | G8: Actual Result | H8: Status | I8: Comments(if any)
A9: TC-MS-01 | B9: View a list of all available slides | C9: - Website is running - Must have administrator account | D9: 1. Open the browser 2. Log in admin 3. Select Slider function | E9: slider.php | F9: Show all existing slides in the website | G9: Show all existing slides in the website | H9: Pass | I9: Error Guessing
A10: TC-MS-02 | B10: Add a new slide to the website | C10: - Website is running - Must have administrator account | D10: 1. Open the browser 2. Log in admin 3. Select Slider function 4.Add necessary slide information | E10: slider.php Slideradd.php | F10: Displays a list of existing slides including newly added slides | G10: Displays a list of existing slides including newly added slides | H10: Pass | I10: Error Guessing
A11: TC-MS-03 | B11: Change the status (On/Off) of a slide | C11: - Website is running - Must have administrator account | D11: 1. Open the browser 2. Log in admin 3. Select Slider function 4. Select "Off or On" status on the tool panel | E11: slider.php | F11: Show new status after change | G11: Error because the ID of the slide | H11: Fail | I11: Error Guessing
A12: TC-MS-04 | B12: Delete an existing slide | C12: - Website is running - Must have administrator account | D12: 1. Open the browser 2. Log in admin 3. Select Slider function 4. Click the "recycle bin" icon to delete the slide | E12: slider.php | F12: Update slide list after deletion | G12: Error because the ID of the slide to be deleted was not found | H12: Fail | I12: Error Guessing
G13: Pass | H13: =COUNTIF(H9:H12,"Pass") -> 2
G14: Fail | H14: =COUNTIF(H9:H12,"Fail") -> 2
G15: Pending | H15: =COUNTIF(H10:H12,"Pending") -> 0
G16: Total | H16: =SUM(H13:H15) -> 4

Sheet Report
A1: TEST REPORT
A2: Test Cycle | B2: System Test
A4: Executed | B4: Passed | F4: =SUM('VPI-Mạnh'!H35,'SP-Mạnh'!H27,'P-Mạnh'!H23,'SPM-Mạnh'!H13,'MC-Mạnh'!H13,'MPR-Mạnh'!H12,'VFP-Mạnh'!H12,'MS-Mạnh'!H13) -> 55
B5: Failed | F5: =SUM('VPI-Mạnh'!H36,'SP-Mạnh'!H28,'P-Mạnh'!H24,'SPM-Mạnh'!H14,'MC-Mạnh'!H14,'MPR-Mạnh'!H13,'VFP-Mạnh'!H13,'MS-Mạnh'!H14) -> 21
B6: (Total) Test executed (Passed + Failed) | F6: =SUM(F4:F5) -> 76
A7: Pending | G7: 0
A8: In Process | G8: 0
A9: Blocked | G9: 0
A10: (Sub-total) Test Planned | G10: =F6 -> 76
A11: Pending + In Process + Blocked + Test Planned | G11: =SUM(G7:G10) -> 76
A13: Function | B13: Description | C13: % TCs Executed | D13: % TCs Passed | E13: % TCs Failed | F13: Priority | G13: Status
A14: View Product Information | B14: View product details including price, size and item information | C14: =('VPI-Mạnh'!H38-'VPI-Mạnh'!H37)/'VPI-Mạnh'!H38 -> 1 | D14: ='VPI-Mạnh'!H35/'VPI-Mạnh'!H38 -> 0.88461538 | E14: ='VPI-Mạnh'!H36/'VPI-Mạnh'!H38 -> 0.11538462 | F14: High | G14: Pass
A15: Search Product | B15: Search for products based on keyword name | C15: =('SP-Mạnh'!H30-'SP-Mạnh'!H29)/'SP-Mạnh'!H30 -> 1 | D15: ='SP-Mạnh'!H27/'SP-Mạnh'!H30 -> 0.72222222 | E15: ='SP-Mạnh'!H28/'SP-Mạnh'!H30 -> 0.27777778 | F15: High | G15: Pass
A16: Purchase | B16: Select information and purchase the item of your choice | C16: =('P-Mạnh'!H26-'P-Mạnh'!H25)/'P-Mạnh'!H26 -> 1 | D16: ='P-Mạnh'!H23/'P-Mạnh'!H26 -> 0.57142857 | E16: ='P-Mạnh'!H24/'P-Mạnh'!H26 -> 0.42857143 | F16: Critical | G16: Unstable
A17: Select Payment Method | B17: Select payment methods to complete the ordering process | C17: =('SPM-Mạnh'!H16-'SPM-Mạnh'!H15)/'SPM-Mạnh'!H16 -> 1 | D17: ='SPM-Mạnh'!H13/'SPM-Mạnh'!H16 -> 0.5 | E17: ='SPM-Mạnh'!H14/'SPM-Mạnh'!H16 -> 0.5 | F17: Critical | G17: Fail
A18: Manage Comments | B18: View, delete comments and commenter information | C18: =('MC-Mạnh'!H16-'MC-Mạnh'!H15)/'MC-Mạnh'!H16 -> 1 | D18: ='MC-Mạnh'!H13/'MC-Mạnh'!H16 -> 0.75 | E18: ='MC-Mạnh'!H14/'MC-Mạnh'!H16 -> 0.25 | F18: Medium | G18: Pass
A19: Manage Product Reviews | B19: View, delete reviews and who rated them | C19: =('MPR-Mạnh'!H15-'MPR-Mạnh'!H14)/'MPR-Mạnh'!H15 -> 1 | D19: ='MPR-Mạnh'!H12/'MPR-Mạnh'!H15 -> 0.66666667 | E19: ='MPR-Mạnh'!H13/'MPR-Mạnh'!H15 -> 0.33333333 | F19: Medium | G19: Unstable
A20: View Favorite Products | B20: View favorite items or remove it | C20: =('VFP-Mạnh'!H15-'VFP-Mạnh'!H14)/'VFP-Mạnh'!H15 -> 1 | D20: ='VFP-Mạnh'!H12/'VFP-Mạnh'!H15 -> 0.66666667 | E20: ='VFP-Mạnh'!H13/'VFP-Mạnh'!H15 -> 0.33333333 | F20: Low–Medium | G20: Fail
A21: Manage Slideshow | B21: Add/Edit/Delete website slideshows | C21: =('MS-Mạnh'!H16-'MS-Mạnh'!H15)/'MS-Mạnh'!H16 -> 1 | D21: ='MS-Mạnh'!H13/'MS-Mạnh'!H16 -> 0.5 | E21: ='MS-Mạnh'!H14/'MS-Mạnh'!H16 -> 0.5 | F21: Low | G21: Pass
